LICENSE
README.md
dj_storage_url/__init__.py
dj_storage_url-0.0.3.dist-info/LICENSE
dj_storage_url-0.0.3.dist-info/METADATA
dj_storage_url-0.0.3.dist-info/WHEEL
dj_storage_url-0.0.3.dist-info/RECORD
